[
  {
    "client_msg_id": "0ee10fd3-af25-4c87-b504-d381474db7f4",
    "type": "message",
    "user": "U03NJ0VSF8A",
    "text": "i'm sorry but i do not understand this lab :slightly_smiling_face:",
    "ts": "1661886729.571129",
    "thread_ts": "1661886729.571129",
    "last_read": "1661887023.661799",
    "subscribed": true,
    "reply_count": 7,
    "replies": [
      {
        "user": "U03P4005U76",
        "ts": "1661886757.701039"
      },
      {
        "user": "U03NF3FU4CD",
        "ts": "1661886793.757449"
      },
      {
        "user": "U03P4005U76",
        "ts": "1661886902.791479"
      },
      {
        "user": "U03NF3FU4CD",
        "ts": "1661886949.025249"
      },
      {
        "user": "U03NF3FU4CD",
        "ts": "1661886957.772299"
      },
      {
        "user": "U03P4005U76",
        "ts": "1661886963.513869"
      },
      {
        "user": "U03NF3FU4CD",
        "ts": "1661887023.661799"
      }
    ],
    "latest_reply": "1661887023.661799",
    "team": "T03NM2X0JCR",
    "replace_original": false,
    "delete_original": false,
    "metadata": {
      "event_type": "",
      "event_payload": null
    },
    "blocks": [
      {
        "type": "rich_text",
        "block_id": "d9p",
        "elements": [
          {
            "type": "rich_text_section",
            "elements": [
              {
                "type": "text",
                "text": "i'm sorry but i do not understand this lab "
              },
              {
                "type": "emoji",
                "name": "slightly_smiling_face",
                "skin_tone": 0
              }
            ]
          }
        ]
      }
    ],
    "user_team": "T03NM2X0JCR",
    "source_team": "T03NM2X0JCR",
    "user_profile": {
      "avatar_hash": "04411a049b06",
      "image_72": "https://avatars.slack-edge.com/2022-07-14/3795254892613_04411a049b06f552bb4d_72.jpg",
      "first_name": "Joshua",
      "real_name": "Joshua LaMorey-Salzmann",
      "display_name": "Joshua",
      "team": "T03NM2X0JCR",
      "name": "lamorey.joshua",
      "is_restricted": false,
      "is_ultra_restricted": false
    },
    "reply_users_count": 2,
    "reply_users": [
      "U03NF3FU4CD",
      "U03P4005U76"
    ]
  },
  {
    "client_msg_id": "27d77dc3-3d54-4c04-9881-5dd703d2711d",
    "type": "message",
    "user": "U03P4005U76",
    "text": "will be there in a sec.",
    "ts": "1661886757.701039",
    "thread_ts": "1661886729.571129",
    "parent_user_id": "U03NJ0VSF8A",
    "team": "T03NM2X0JCR",
    "replace_original": false,
    "delete_original": false,
    "metadata": {
      "event_type": "",
      "event_payload": null
    },
    "blocks": [
      {
        "type": "rich_text",
        "block_id": "+gW",
        "elements": [
          {
            "type": "rich_text_section",
            "elements": [
              {
                "type": "text",
                "text": "will be there in a sec."
              }
            ]
          }
        ]
      }
    ],
    "user_team": "T03NM2X0JCR",
    "source_team": "T03NM2X0JCR",
    "user_profile": {
      "avatar_hash": "19c4be189f84",
      "image_72": "https://avatars.slack-edge.com/2022-07-11/3783657200355_19c4be189f84d880b03e_72.jpg",
      "first_name": "Rico",
      "real_name": "Rico Trebeljahr",
      "display_name": "Rico Trebeljahr",
      "team": "T03NM2X0JCR",
      "name": "rico.trebeljahr",
      "is_restricted": false,
      "is_ultra_restricted": false
    },
    "reply_users_count": 0,
    "reply_users": null
  },
  {
    "client_msg_id": "2ab9940e-e684-4bdd-84d0-bafa462d6157",
    "type": "message",
    "user": "U03NF3FU4CD",
    "text": "I would join you if possible :smile:",
    "ts": "1661886793.757449",
    "thread_ts": "1661886729.571129",
    "parent_user_id": "U03NJ0VSF8A",
    "team": "T03NM2X0JCR",
    "reactions": [
      {
        "name": "+1::skin-tone-3",
        "count": 1,
        "users": [
          "U03NJ0VSF8A"
        ]
      }
    ],
    "replace_original": false,
    "delete_original": false,
    "metadata": {
      "event_type": "",
      "event_payload": null
    },
    "blocks": [
      {
        "type": "rich_text",
        "block_id": "+Mu",
        "elements": [
          {
            "type": "rich_text_section",
            "elements": [
              {
                "type": "text",
                "text": "I would join you if possible "
              },
              {
                "type": "emoji",
                "name": "smile",
                "skin_tone": 0
              }
            ]
          }
        ]
      }
    ],
    "user_team": "T03NM2X0JCR",
    "source_team": "T03NM2X0JCR",
    "user_profile": {
      "avatar_hash": "gffbd1f8138d",
      "image_72": "https://secure.gravatar.com/avatar/ffbd1f8138d8ce7282914f927aa4c382.jpg?s=72\u0026d=https%3A%2F%2Fa.slack-edge.com%2Fdf10d%2Fimg%2Favatars%2Fava_0000-72.png",
      "first_name": "Hector",
      "real_name": "Hector Fernandez",
      "display_name": "",
      "team": "T03NM2X0JCR",
      "name": "hfernandez04",
      "is_restricted": false,
      "is_ultra_restricted": false
    },
    "reply_users_count": 0,
    "reply_users": null
  },
  {
    "client_msg_id": "385f650c-7230-4449-a2bc-13bc81472206",
    "type": "message",
    "user": "U03P4005U76",
    "text": "come over if you want to join.",
    "ts": "1661886902.791479",
    "thread_ts": "1661886729.571129",
    "parent_user_id": "U03NJ0VSF8A",
    "team": "T03NM2X0JCR",
    "replace_original": false,
    "delete_original": false,
    "metadata": {
      "event_type": "",
      "event_payload": null
    },
    "blocks": [
      {
        "type": "rich_text",
        "block_id": "J4GC",
        "elements": [
          {
            "type": "rich_text_section",
            "elements": [
              {
                "type": "text",
                "text": "come over if you want to join."
              }
            ]
          }
        ]
      }
    ],
    "user_team": "T03NM2X0JCR",
    "source_team": "T03NM2X0JCR",
    "user_profile": {
      "avatar_hash": "19c4be189f84",
      "image_72": "https://avatars.slack-edge.com/2022-07-11/3783657200355_19c4be189f84d880b03e_72.jpg",
      "first_name": "Rico",
      "real_name": "Rico Trebeljahr",
      "display_name": "Rico Trebeljahr",
      "team": "T03NM2X0JCR",
      "name": "rico.trebeljahr",
      "is_restricted": false,
      "is_ultra_restricted": false
    },
    "reply_users_count": 0,
    "reply_users": null
  },
  {
    "client_msg_id": "3a98ae92-6c8c-4f5b-ace3-9d3566549f96",
    "type": "message",
    "user": "U03NF3FU4CD",
    "text": "which room?",
    "ts": "1661886949.025249",
    "thread_ts": "1661886729.571129",
    "parent_user_id": "U03NJ0VSF8A",
    "team": "T03NM2X0JCR",
    "replace_original": false,
    "delete_original": false,
    "metadata": {
      "event_type": "",
      "event_payload": null
    },
    "blocks": [
      {
        "type": "rich_text",
        "block_id": "4Vc6",
        "elements": [
          {
            "type": "rich_text_section",
            "elements": [
              {
                "type": "text",
                "text": "which room?"
              }
            ]
          }
        ]
      }
    ],
    "user_team": "T03NM2X0JCR",
    "source_team": "T03NM2X0JCR",
    "user_profile": {
      "avatar_hash": "gffbd1f8138d",
      "image_72": "https://secure.gravatar.com/avatar/ffbd1f8138d8ce7282914f927aa4c382.jpg?s=72\u0026d=https%3A%2F%2Fa.slack-edge.com%2Fdf10d%2Fimg%2Favatars%2Fava_0000-72.png",
      "first_name": "Hector",
      "real_name": "Hector Fernandez",
      "display_name": "",
      "team": "T03NM2X0JCR",
      "name": "hfernandez04",
      "is_restricted": false,
      "is_ultra_restricted": false
    },
    "reply_users_count": 0,
    "reply_users": null
  },
  {
    "client_msg_id": "df7ab60e-9686-4007-bbd3-7b55f509fa71",
    "type": "message",
    "user": "U03NF3FU4CD",
    "text": "i hate zoom haha",
    "ts": "1661886957.772299",
    "thread_ts": "1661886729.571129",
    "parent_user_id": "U03NJ0VSF8A",
    "team": "T03NM2X0JCR",
    "replace_original": false,
    "delete_original": false,
    "metadata": {
      "event_type": "",
      "event_payload": null
    },
    "blocks": [
      {
        "type": "rich_text",
        "block_id": "vEkpo",
        "elements": [
          {
            "type": "rich_text_section",
            "elements": [
              {
                "type": "text",
                "text": "i hate zoom haha"
              }
            ]
          }
        ]
      }
    ],
    "user_team": "T03NM2X0JCR",
    "source_team": "T03NM2X0JCR",
    "user_profile": {
      "avatar_hash": "gffbd1f8138d",
      "image_72": "https://secure.gravatar.com/avatar/ffbd1f8138d8ce7282914f927aa4c382.jpg?s=72\u0026d=https%3A%2F%2Fa.slack-edge.com%2Fdf10d%2Fimg%2Favatars%2Fava_0000-72.png",
      "first_name": "Hector",
      "real_name": "Hector Fernandez",
      "display_name": "",
      "team": "T03NM2X0JCR",
      "name": "hfernandez04",
      "is_restricted": false,
      "is_ultra_restricted": false
    },
    "reply_users_count": 0,
    "reply_users": null
  },
  {
    "client_msg_id": "5b140d4c-1b6b-453d-8dd4-82d166833b8d",
    "type": "message",
    "user": "U03P4005U76",
    "text": "3",
    "ts": "1661886963.513869",
    "thread_ts": "1661886729.571129",
    "parent_user_id": "U03NJ0VSF8A",
    "team": "T03NM2X0JCR",
    "replace_original": false,
    "delete_original": false,
    "metadata": {
      "event_type": "",
      "event_payload": null
    },
    "blocks": [
      {
        "type": "rich_text",
        "block_id": "Wv4N",
        "elements": [
          {
            "type": "rich_text_section",
            "elements": [
              {
                "type": "text",
                "text": "3"
              }
            ]
          }
        ]
      }
    ],
    "user_team": "T03NM2X0JCR",
    "source_team": "T03NM2X0JCR",
    "user_profile": {
      "avatar_hash": "19c4be189f84",
      "image_72": "https://avatars.slack-edge.com/2022-07-11/3783657200355_19c4be189f84d880b03e_72.jpg",
      "first_name": "Rico",
      "real_name": "Rico Trebeljahr",
      "display_name": "Rico Trebeljahr",
      "team": "T03NM2X0JCR",
      "name": "rico.trebeljahr",
      "is_restricted": false,
      "is_ultra_restricted": false
    },
    "reply_users_count": 0,
    "reply_users": null
  },
  {
    "client_msg_id": "f4f581b2-ccbc-4944-b6b4-7d1afcbbfb41",
    "type": "message",
    "user": "U03NF3FU4CD",
    "text": "i just can go to mine. Number 6",
    "ts": "1661887023.661799",
    "thread_ts": "1661886729.571129",
    "parent_user_id": "U03NJ0VSF8A",
    "team": "T03NM2X0JCR",
    "replace_original": false,
    "delete_original": false,
    "metadata": {
      "event_type": "",
      "event_payload": null
    },
    "blocks": [
      {
        "type": "rich_text",
        "block_id": "A=l",
        "elements": [
          {
            "type": "rich_text_section",
            "elements": [
              {
                "type": "text",
                "text": "i just can go to mine. Number 6"
              }
            ]
          }
        ]
      }
    ],
    "user_team": "T03NM2X0JCR",
    "source_team": "T03NM2X0JCR",
    "user_profile": {
      "avatar_hash": "gffbd1f8138d",
      "image_72": "https://secure.gravatar.com/avatar/ffbd1f8138d8ce7282914f927aa4c382.jpg?s=72\u0026d=https%3A%2F%2Fa.slack-edge.com%2Fdf10d%2Fimg%2Favatars%2Fava_0000-72.png",
      "first_name": "Hector",
      "real_name": "Hector Fernandez",
      "display_name": "",
      "team": "T03NM2X0JCR",
      "name": "hfernandez04",
      "is_restricted": false,
      "is_ultra_restricted": false
    },
    "reply_users_count": 0,
    "reply_users": null
  },
  {
    "client_msg_id": "633ef15a-9bdb-42b7-92e9-aab54b030b0d",
    "type": "message",
    "user": "U03NBCRJ99U",
    "text": "function func1(step,callback) {\n  getInstruction( \"mashedPotatoes\", step,\n    (val) =\u0026gt; document.querySelector(\"#mashedPotatoes\").innerHTML += `\u0026lt;li\u0026gt;${val}\u0026lt;/li\u0026gt;`,\n    (error) =\u0026gt; console.log(error)\n  );\n  callback();\n}\n\nfunc1(0, () =\u0026gt; {\n  func1(1, () =\u0026gt; {\n    func1(2, () =\u0026gt; {\n      func1(3, () =\u0026gt; {\n        func1(4, () =\u0026gt; {\n          func1(5, () =\u0026gt; {});\n        });\n      });\n    });\n  });\n});",
    "ts": "1661888185.724249",
    "thread_ts": "1661888185.724249",
    "last_read": "1661888847.080459",
    "subscribed": true,
    "reply_count": 12,
    "replies": [
      {
        "user": "U03P4005U76",
        "ts": "1661888456.455629"
      },
      {
        "user": "U03P4005U76",
        "ts": "1661888477.926079"
      },
      {
        "user": "U03NBCRJ99U",
        "ts": "1661888548.565689"
      },
      {
        "user": "U03NBCRJ99U",
        "ts": "1661888549.962559"
      },
      {
        "user": "U03NBCRJ99U",
        "ts": "1661888566.217219"
      },
      {
        "user": "U03P4005U76",
        "ts": "1661888657.225089"
      },
      {
        "user": "U03P4005U76",
        "ts": "1661888685.026689"
      },
      {
        "user": "U03NBCRJ99U",
        "ts": "1661888686.548299"
      },
      {
        "user": "U03P4005U76",
        "ts": "1661888688.638599"
      },
      {
        "user": "U03P4005U76",
        "ts": "1661888697.038979"
      },
      {
        "user": "U03NBCRJ99U",
        "ts": "1661888837.592229"
      },
      {
        "user": "U03P4005U76",
        "ts": "1661888847.080459"
      }
    ],
    "latest_reply": "1661888847.080459",
    "team": "T03NM2X0JCR",
    "reactions": [
      {
        "name": "eyes",
        "count": 1,
        "users": [
          "U03P4005U76"
        ]
      }
    ],
    "replace_original": false,
    "delete_original": false,
    "metadata": {
      "event_type": "",
      "event_payload": null
    },
    "blocks": [
      {
        "type": "rich_text",
        "block_id": "zYL",
        "elements": [
          {
            "type": "rich_text_section",
            "elements": [
              {
                "type": "text",
                "text": "function func1(step,callback) {\n  getInstruction( \"mashedPotatoes\", step,\n    (val) =\u003e document.querySelector(\"#mashedPotatoes\").innerHTML += `\u003cli\u003e${val}\u003c/li\u003e`,\n    (error) =\u003e console.log(error)\n  );\n  callback();\n}\n\nfunc1(0, () =\u003e {\n  func1(1, () =\u003e {\n    func1(2, () =\u003e {\n      func1(3, () =\u003e {\n        func1(4, () =\u003e {\n          func1(5, () =\u003e {});\n        });\n      });\n    });\n  });\n});"
              }
            ]
          }
        ]
      }
    ],
    "user_team": "T03NM2X0JCR",
    "source_team": "T03NM2X0JCR",
    "user_profile": {
      "avatar_hash": "g573a376398a",
      "image_72": "https://secure.gravatar.com/avatar/573a376398a82acb061e12fb20ba25f7.jpg?s=72\u0026d=https%3A%2F%2Fa.slack-edge.com%2Fdf10d%2Fimg%2Favatars%2Fava_0010-72.png",
      "first_name": "Antonio",
      "real_name": "Antonio Vara Piquer",
      "display_name": "",
      "team": "T03NM2X0JCR",
      "name": "ghezath",
      "is_restricted": false,
      "is_ultra_restricted": false
    },
    "reply_users_count": 2,
    "reply_users": [
      "U03NBCRJ99U",
      "U03P4005U76"
    ]
  },
  {
    "client_msg_id": "cd4c2a3b-49a3-4f79-a9b4-04f7d0cef9e3",
    "type": "message",
    "user": "U03NBCRJ99U",
    "text": "trying that is not synchronized",
    "ts": "1661888208.034869",
    "team": "T03NM2X0JCR",
    "replace_original": false,
    "delete_original": false,
    "metadata": {
      "event_type": "",
      "event_payload": null
    },
    "blocks": [
      {
        "type": "rich_text",
        "block_id": "F=PT",
        "elements": [
          {
            "type": "rich_text_section",
            "elements": [
              {
                "type": "text",
                "text": "trying that is not synchronized"
              }
            ]
          }
        ]
      }
    ],
    "user_team": "T03NM2X0JCR",
    "source_team": "T03NM2X0JCR",
    "user_profile": {
      "avatar_hash": "g573a376398a",
      "image_72": "https://secure.gravatar.com/avatar/573a376398a82acb061e12fb20ba25f7.jpg?s=72\u0026d=https%3A%2F%2Fa.slack-edge.com%2Fdf10d%2Fimg%2Favatars%2Fava_0010-72.png",
      "first_name": "Antonio",
      "real_name": "Antonio Vara Piquer",
      "display_name": "",
      "team": "T03NM2X0JCR",
      "name": "ghezath",
      "is_restricted": false,
      "is_ultra_restricted": false
    },
    "reply_users_count": 0,
    "reply_users": null
  },
  {
    "client_msg_id": "8788a8fa-a316-45d3-a423-e72fe8a6cd64",
    "type": "message",
    "user": "U03NBCRJ99U",
    "text": "anyone can help?",
    "ts": "1661888223.196439",
    "team": "T03NM2X0JCR",
    "replace_original": false,
    "delete_original": false,
    "metadata": {
      "event_type": "",
      "event_payload": null
    },
    "blocks": [
      {
        "type": "rich_text",
        "block_id": "nUVn",
        "elements": [
          {
            "type": "rich_text_section",
            "elements": [
              {
                "type": "text",
                "text": "anyone can help?"
              }
            ]
          }
        ]
      }
    ],
    "user_team": "T03NM2X0JCR",
    "source_team": "T03NM2X0JCR",
    "user_profile": {
      "avatar_hash": "g573a376398a",
      "image_72": "https://secure.gravatar.com/avatar/573a376398a82acb061e12fb20ba25f7.jpg?s=72\u0026d=https%3A%2F%2Fa.slack-edge.com%2Fdf10d%2Fimg%2Favatars%2Fava_0010-72.png",
      "first_name": "Antonio",
      "real_name": "Antonio Vara Piquer",
      "display_name": "",
      "team": "T03NM2X0JCR",
      "name": "ghezath",
      "is_restricted": false,
      "is_ultra_restricted": false
    },
    "reply_users_count": 0,
    "reply_users": null
  },
  {
    "client_msg_id": "b0dabeb8-8796-47ac-9872-d065c986b7f4",
    "type": "message",
    "user": "U03P4005U76",
    "text": "so, the problem is that you are not passing in the callback into the getInstruction correctly.",
    "ts": "1661888456.455629",
    "thread_ts": "1661888185.724249",
    "parent_user_id": "U03NBCRJ99U",
    "team": "T03NM2X0JCR",
    "replace_original": false,
    "delete_original": false,
    "metadata": {
      "event_type": "",
      "event_payload": null
    },
    "blocks": [
      {
        "type": "rich_text",
        "block_id": "JfCX",
        "elements": [
          {
            "type": "rich_text_section",
            "elements": [
              {
                "type": "text",
                "text": "so, the problem is that you are not passing in the callback into the getInstruction correctly."
              }
            ]
          }
        ]
      }
    ],
    "user_team": "T03NM2X0JCR",
    "source_team": "T03NM2X0JCR",
    "user_profile": {
      "avatar_hash": "19c4be189f84",
      "image_72": "https://avatars.slack-edge.com/2022-07-11/3783657200355_19c4be189f84d880b03e_72.jpg",
      "first_name": "Rico",
      "real_name": "Rico Trebeljahr",
      "display_name": "Rico Trebeljahr",
      "team": "T03NM2X0JCR",
      "name": "rico.trebeljahr",
      "is_restricted": false,
      "is_ultra_restricted": false
    },
    "reply_users_count": 0,
    "reply_users": null
  },
  {
    "client_msg_id": "ca55d074-49f7-48aa-9067-22e9c642d7ac",
    "type": "message",
    "user": "U03P4005U76",
    "text": "if you look at getInstruction you see that the way it works is by getting 4 arguments, 2 of them being callbacks.",
    "ts": "1661888477.926079",
    "thread_ts": "1661888185.724249",
    "parent_user_id": "U03NBCRJ99U",
    "team": "T03NM2X0JCR",
    "replace_original": false,
    "delete_original": false,
    "metadata": {
      "event_type": "",
      "event_payload": null
    },
    "blocks": [
      {
        "type": "rich_text",
        "block_id": "Aub",
        "elements": [
          {
            "type": "rich_text_section",
            "elements": [
              {
                "type": "text",
                "text": "if you look at getInstruction you see that the way it works is by getting 4 arguments, 2 of them being callbacks."
              }
            ]
          }
        ]
      }
    ],
    "user_team": "T03NM2X0JCR",
    "source_team": "T03NM2X0JCR",
    "user_profile": {
      "avatar_hash": "19c4be189f84",
      "image_72": "https://avatars.slack-edge.com/2022-07-11/3783657200355_19c4be189f84d880b03e_72.jpg",
      "first_name": "Rico",
      "real_name": "Rico Trebeljahr",
      "display_name": "Rico Trebeljahr",
      "team": "T03NM2X0JCR",
      "name": "rico.trebeljahr",
      "is_restricted": false,
      "is_ultra_restricted": false
    },
    "reply_users_count": 0,
    "reply_users": null
  },
  {
    "client_msg_id": "809b9e59-95fa-486c-8946-a8e02927a66e",
    "type": "message",
    "user": "U03NBCRJ99U",
    "text": "but i have created",
    "ts": "1661888548.565689",
    "thread_ts": "1661888185.724249",
    "parent_user_id": "U03NBCRJ99U",
    "team": "T03NM2X0JCR",
    "replace_original": false,
    "delete_original": false,
    "metadata": {
      "event_type": "",
      "event_payload": null
    },
    "blocks": [
      {
        "type": "rich_text",
        "block_id": "VC/",
        "elements": [
          {
            "type": "rich_text_section",
            "elements": [
              {
                "type": "text",
                "text": "but i have created"
              }
            ]
          }
        ]
      }
    ],
    "user_team": "T03NM2X0JCR",
    "source_team": "T03NM2X0JCR",
    "user_profile": {
      "avatar_hash": "g573a376398a",
      "image_72": "https://secure.gravatar.com/avatar/573a376398a82acb061e12fb20ba25f7.jpg?s=72\u0026d=https%3A%2F%2Fa.slack-edge.com%2Fdf10d%2Fimg%2Favatars%2Fava_0010-72.png",
      "first_name": "Antonio",
      "real_name": "Antonio Vara Piquer",
      "display_name": "",
      "team": "T03NM2X0JCR",
      "name": "ghezath",
      "is_restricted": false,
      "is_ultra_restricted": false
    },
    "reply_users_count": 0,
    "reply_users": null
  },
  {
    "client_msg_id": "469e7431-b311-4e62-9d61-53cd4c146402",
    "type": "message",
    "user": "U03NBCRJ99U",
    "text": "function func1(step,callback) {\n  getInstruction( \"mashedPotatoes\", step,\n    (val) =\u0026gt; document.querySelector(\"#mashedPotatoes\").innerHTML += `\u0026lt;li\u0026gt;${val}\u0026lt;/li\u0026gt;`,\n    (error) =\u0026gt; console.log(error)\n  );\n  callback();\n}",
    "ts": "1661888549.962559",
    "thread_ts": "1661888185.724249",
    "parent_user_id": "U03NBCRJ99U",
    "team": "T03NM2X0JCR",
    "replace_original": false,
    "delete_original": false,
    "metadata": {
      "event_type": "",
      "event_payload": null
    },
    "blocks": [
      {
        "type": "rich_text",
        "block_id": "J7T2",
        "elements": [
          {
            "type": "rich_text_section",
            "elements": [
              {
                "type": "text",
                "text": "function func1(step,callback) {\n  getInstruction( \"mashedPotatoes\", step,\n    (val) =\u003e document.querySelector(\"#mashedPotatoes\").innerHTML += `\u003cli\u003e${val}\u003c/li\u003e`,\n    (error) =\u003e console.log(error)\n  );\n  callback();\n}"
              }
            ]
          }
        ]
      }
    ],
    "user_team": "T03NM2X0JCR",
    "source_team": "T03NM2X0JCR",
    "user_profile": {
      "avatar_hash": "g573a376398a",
      "image_72": "https://secure.gravatar.com/avatar/573a376398a82acb061e12fb20ba25f7.jpg?s=72\u0026d=https%3A%2F%2Fa.slack-edge.com%2Fdf10d%2Fimg%2Favatars%2Fava_0010-72.png",
      "first_name": "Antonio",
      "real_name": "Antonio Vara Piquer",
      "display_name": "",
      "team": "T03NM2X0JCR",
      "name": "ghezath",
      "is_restricted": false,
      "is_ultra_restricted": false
    },
    "reply_users_count": 0,
    "reply_users": null
  },
  {
    "client_msg_id": "1c8e618f-e45a-4325-8082-6701d77fc98f",
    "type": "message",
    "user": "U03NBCRJ99U",
    "text": "only with 2 param",
    "ts": "1661888566.217219",
    "thread_ts": "1661888185.724249",
    "parent_user_id": "U03NBCRJ99U",
    "team": "T03NM2X0JCR",
    "replace_original": false,
    "delete_original": false,
    "metadata": {
      "event_type": "",
      "event_payload": null
    },
    "blocks": [
      {
        "type": "rich_text",
        "block_id": "z2=Nt",
        "elements": [
          {
            "type": "rich_text_section",
            "elements": [
              {
                "type": "text",
                "text": "only with 2 param"
              }
            ]
          }
        ]
      }
    ],
    "user_team": "T03NM2X0JCR",
    "source_team": "T03NM2X0JCR",
    "user_profile": {
      "avatar_hash": "g573a376398a",
      "image_72": "https://secure.gravatar.com/avatar/573a376398a82acb061e12fb20ba25f7.jpg?s=72\u0026d=https%3A%2F%2Fa.slack-edge.com%2Fdf10d%2Fimg%2Favatars%2Fava_0010-72.png",
      "first_name": "Antonio",
      "real_name": "Antonio Vara Piquer",
      "display_name": "",
      "team": "T03NM2X0JCR",
      "name": "ghezath",
      "is_restricted": false,
      "is_ultra_restricted": false
    },
    "reply_users_count": 0,
    "reply_users": null
  },
  {
    "client_msg_id": "5c7e911b-be04-426a-8be2-b784be9b558d",
    "type": "message",
    "user": "U03P4005U76",
    "text": "which calls callback at the same time it calls getInstruction.\n\nYour flow of program therefore will look something like this:\n\nfunc1 -\u0026gt; func1 -\u0026gt; func1 -\u0026gt; func1 -\u0026gt; func1 -\u0026gt; func1. each time func1 is called you will create a new setTimeout. So you create 6 set timeouts at pretty much the same time.",
    "ts": "1661888657.225089",
    "thread_ts": "1661888185.724249",
    "parent_user_id": "U03NBCRJ99U",
    "team": "T03NM2X0JCR",
    "replace_original": false,
    "delete_original": false,
    "metadata": {
      "event_type": "",
      "event_payload": null
    },
    "blocks": [
      {
        "type": "rich_text",
        "block_id": "fRzO",
        "elements": [
          {
            "type": "rich_text_section",
            "elements": [
              {
                "type": "text",
                "text": "which calls callback at the same time it calls getInstruction.\n\nYour flow of program therefore will look something like this:\n\nfunc1 -\u003e func1 -\u003e func1 -\u003e func1 -\u003e func1 -\u003e func1. each time func1 is called you will create a new setTimeout. So you create 6 set timeouts at pretty much the same time."
              }
            ]
          }
        ]
      }
    ],
    "user_team": "T03NM2X0JCR",
    "source_team": "T03NM2X0JCR",
    "user_profile": {
      "avatar_hash": "19c4be189f84",
      "image_72": "https://avatars.slack-edge.com/2022-07-11/3783657200355_19c4be189f84d880b03e_72.jpg",
      "first_name": "Rico",
      "real_name": "Rico Trebeljahr",
      "display_name": "Rico Trebeljahr",
      "team": "T03NM2X0JCR",
      "name": "rico.trebeljahr",
      "is_restricted": false,
      "is_ultra_restricted": false
    },
    "reply_users_count": 0,
    "reply_users": null
  },
  {
    "client_msg_id": "0a48dd99-d927-4d73-8c85-04f5a95864b3",
    "type": "message",
    "user": "U03P4005U76",
    "text": "the trick to change your func1 to work is to include your \"callback\" parameter into the callback passed into getInstruction as an argument.",
    "ts": "1661888685.026689",
    "thread_ts": "1661888185.724249",
    "parent_user_id": "U03NBCRJ99U",
    "team": "T03NM2X0JCR",
    "replace_original": false,
    "delete_original": false,
    "metadata": {
      "event_type": "",
      "event_payload": null
    },
    "blocks": [
      {
        "type": "rich_text",
        "block_id": "GbZ",
        "elements": [
          {
            "type": "rich_text_section",
            "elements": [
              {
                "type": "text",
                "text": "the trick to change your func1 to work is to include your \"callback\" parameter into the callback passed into getInstruction as an argument."
              }
            ]
          }
        ]
      }
    ],
    "user_team": "T03NM2X0JCR",
    "source_team": "T03NM2X0JCR",
    "user_profile": {
      "avatar_hash": "19c4be189f84",
      "image_72": "https://avatars.slack-edge.com/2022-07-11/3783657200355_19c4be189f84d880b03e_72.jpg",
      "first_name": "Rico",
      "real_name": "Rico Trebeljahr",
      "display_name": "Rico Trebeljahr",
      "team": "T03NM2X0JCR",
      "name": "rico.trebeljahr",
      "is_restricted": false,
      "is_ultra_restricted": false
    },
    "reply_users_count": 0,
    "reply_users": null
  },
  {
    "client_msg_id": "5e23091d-47e1-4ac1-ab3b-ed5090542cbd",
    "type": "message",
    "user": "U03NBCRJ99U",
    "text": "ok, got it",
    "ts": "1661888686.548299",
    "thread_ts": "1661888185.724249",
    "parent_user_id": "U03NBCRJ99U",
    "team": "T03NM2X0JCR",
    "replace_original": false,
    "delete_original": false,
    "metadata": {
      "event_type": "",
      "event_payload": null
    },
    "blocks": [
      {
        "type": "rich_text",
        "block_id": "ornp",
        "elements": [
          {
            "type": "rich_text_section",
            "elements": [
              {
                "type": "text",
                "text": "ok, got it"
              }
            ]
          }
        ]
      }
    ],
    "user_team": "T03NM2X0JCR",
    "source_team": "T03NM2X0JCR",
    "user_profile": {
      "avatar_hash": "g573a376398a",
      "image_72": "https://secure.gravatar.com/avatar/573a376398a82acb061e12fb20ba25f7.jpg?s=72\u0026d=https%3A%2F%2Fa.slack-edge.com%2Fdf10d%2Fimg%2Favatars%2Fava_0010-72.png",
      "first_name": "Antonio",
      "real_name": "Antonio Vara Piquer",
      "display_name": "",
      "team": "T03NM2X0JCR",
      "name": "ghezath",
      "is_restricted": false,
      "is_ultra_restricted": false
    },
    "reply_users_count": 0,
    "reply_users": null
  },
  {
    "client_msg_id": "967521b3-1d3e-4ac3-9e80-6816ff958450",
    "type": "message",
    "user": "U03P4005U76",
    "text": "something like this:",
    "ts": "1661888688.638599",
    "thread_ts": "1661888185.724249",
    "parent_user_id": "U03NBCRJ99U",
    "team": "T03NM2X0JCR",
    "replace_original": false,
    "delete_original": false,
    "metadata": {
      "event_type": "",
      "event_payload": null
    },
    "blocks": [
      {
        "type": "rich_text",
        "block_id": "q9yJ",
        "elements": [
          {
            "type": "rich_text_section",
            "elements": [
              {
                "type": "text",
                "text": "something like this:"
              }
            ]
          }
        ]
      }
    ],
    "user_team": "T03NM2X0JCR",
    "source_team": "T03NM2X0JCR",
    "user_profile": {
      "avatar_hash": "19c4be189f84",
      "image_72": "https://avatars.slack-edge.com/2022-07-11/3783657200355_19c4be189f84d880b03e_72.jpg",
      "first_name": "Rico",
      "real_name": "Rico Trebeljahr",
      "display_name": "Rico Trebeljahr",
      "team": "T03NM2X0JCR",
      "name": "rico.trebeljahr",
      "is_restricted": false,
      "is_ultra_restricted": false
    },
    "reply_users_count": 0,
    "reply_users": null
  },
  {
    "client_msg_id": "ed7bd81c-8370-4cd2-a102-ac35d2187d55",
    "type": "message",
    "user": "U03P4005U76",
    "text": "function func1(_step_, _callback_) {\n  const htmlEdit = (_val_) =\u0026gt;\n    (document.querySelector(\"#mashedPotatoes\").innerHTML += `\u0026lt;li\u0026gt;${_val_}\u0026lt;/li\u0026gt;`);\n  getInstruction(\n    \"mashedPotatoes\",\n    _step_,\n    (_val_) =\u0026gt; {\n      htmlEdit(_val_);\n      callback();\n    },\n    (_error_) =\u0026gt; console.log(_error_)\n  );\n}",
    "ts": "1661888697.038979",
    "thread_ts": "1661888185.724249",
    "parent_user_id": "U03NBCRJ99U",
    "team": "T03NM2X0JCR",
    "replace_original": false,
    "delete_original": false,
    "metadata": {
      "event_type": "",
      "event_payload": null
    },
    "blocks": [
      {
        "type": "rich_text",
        "block_id": "pBSHS",
        "elements": [
          {
            "type": "rich_text_section",
            "elements": [
              {
                "type": "text",
                "text": "function func1("
              },
              {
                "type": "text",
                "text": "step",
                "style": {
                  "italic": true
                }
              },
              {
                "type": "text",
                "text": ", "
              },
              {
                "type": "text",
                "text": "callback",
                "style": {
                  "italic": true
                }
              },
              {
                "type": "text",
                "text": ") {\n  const htmlEdit = ("
              },
              {
                "type": "text",
                "text": "val",
                "style": {
                  "italic": true
                }
              },
              {
                "type": "text",
                "text": ") =\u003e\n    (document.querySelector(\"#mashedPotatoes\").innerHTML += `\u003cli\u003e${"
              },
              {
                "type": "text",
                "text": "val",
                "style": {
                  "italic": true
                }
              },
              {
                "type": "text",
                "text": "}\u003c/li\u003e`);\n  getInstruction(\n    \"mashedPotatoes\",\n    "
              },
              {
                "type": "text",
                "text": "step",
                "style": {
                  "italic": true
                }
              },
              {
                "type": "text",
                "text": ",\n    ("
              },
              {
                "type": "text",
                "text": "val",
                "style": {
                  "italic": true
                }
              },
              {
                "type": "text",
                "text": ") =\u003e {\n      htmlEdit("
              },
              {
                "type": "text",
                "text": "val",
                "style": {
                  "italic": true
                }
              },
              {
                "type": "text",
                "text": ");\n      callback();\n    },\n    ("
              },
              {
                "type": "text",
                "text": "error",
                "style": {
                  "italic": true
                }
              },
              {
                "type": "text",
                "text": ") =\u003e console.log("
              },
              {
                "type": "text",
                "text": "error",
                "style": {
                  "italic": true
                }
              },
              {
                "type": "text",
                "text": ")\n  );\n}"
              }
            ]
          }
        ]
      }
    ],
    "user_team": "T03NM2X0JCR",
    "source_team": "T03NM2X0JCR",
    "user_profile": {
      "avatar_hash": "19c4be189f84",
      "image_72": "https://avatars.slack-edge.com/2022-07-11/3783657200355_19c4be189f84d880b03e_72.jpg",
      "first_name": "Rico",
      "real_name": "Rico Trebeljahr",
      "display_name": "Rico Trebeljahr",
      "team": "T03NM2X0JCR",
      "name": "rico.trebeljahr",
      "is_restricted": false,
      "is_ultra_restricted": false
    },
    "reply_users_count": 0,
    "reply_users": null
  },
  {
    "client_msg_id": "61df0e32-4e09-4272-ac8b-6218653629fc",
    "type": "message",
    "user": "U03NBCRJ99U",
    "text": "Thanks!",
    "ts": "1661888837.592229",
    "thread_ts": "1661888185.724249",
    "parent_user_id": "U03NBCRJ99U",
    "team": "T03NM2X0JCR",
    "replace_original": false,
    "delete_original": false,
    "metadata": {
      "event_type": "",
      "event_payload": null
    },
    "blocks": [
      {
        "type": "rich_text",
        "block_id": "6WWKi",
        "elements": [
          {
            "type": "rich_text_section",
            "elements": [
              {
                "type": "text",
                "text": "Thanks!"
              }
            ]
          }
        ]
      }
    ],
    "user_team": "T03NM2X0JCR",
    "source_team": "T03NM2X0JCR",
    "user_profile": {
      "avatar_hash": "g573a376398a",
      "image_72": "https://secure.gravatar.com/avatar/573a376398a82acb061e12fb20ba25f7.jpg?s=72\u0026d=https%3A%2F%2Fa.slack-edge.com%2Fdf10d%2Fimg%2Favatars%2Fava_0010-72.png",
      "first_name": "Antonio",
      "real_name": "Antonio Vara Piquer",
      "display_name": "",
      "team": "T03NM2X0JCR",
      "name": "ghezath",
      "is_restricted": false,
      "is_ultra_restricted": false
    },
    "reply_users_count": 0,
    "reply_users": null
  },
  {
    "client_msg_id": "6e5e532a-0aeb-41e9-ab18-ae43ada0db39",
    "type": "message",
    "user": "U03P4005U76",
    "text": "no problem :slightly_smiling_face:",
    "ts": "1661888847.080459",
    "thread_ts": "1661888185.724249",
    "parent_user_id": "U03NBCRJ99U",
    "team": "T03NM2X0JCR",
    "replace_original": false,
    "delete_original": false,
    "metadata": {
      "event_type": "",
      "event_payload": null
    },
    "blocks": [
      {
        "type": "rich_text",
        "block_id": "RaaI",
        "elements": [
          {
            "type": "rich_text_section",
            "elements": [
              {
                "type": "text",
                "text": "no problem "
              },
              {
                "type": "emoji",
                "name": "slightly_smiling_face",
                "skin_tone": 0
              }
            ]
          }
        ]
      }
    ],
    "user_team": "T03NM2X0JCR",
    "source_team": "T03NM2X0JCR",
    "user_profile": {
      "avatar_hash": "19c4be189f84",
      "image_72": "https://avatars.slack-edge.com/2022-07-11/3783657200355_19c4be189f84d880b03e_72.jpg",
      "first_name": "Rico",
      "real_name": "Rico Trebeljahr",
      "display_name": "Rico Trebeljahr",
      "team": "T03NM2X0JCR",
      "name": "rico.trebeljahr",
      "is_restricted": false,
      "is_ultra_restricted": false
    },
    "reply_users_count": 0,
    "reply_users": null
  },
  {
    "client_msg_id": "7ad0cd95-a292-47d5-bd19-663707792f4f",
    "type": "message",
    "user": "U03P4005U76",
    "text": "just a quick note on the lab: the last bonus is a bit stupid in my opinion... you don't have to bother about it too much, because Promise.all in this context doesn't quite work in the \"correct\" way. because it's not sequential at all.",
    "ts": "1661890083.559969",
    "thread_ts": "1661890083.559969",
    "edited": {
      "user": "U03P4005U76",
      "ts": "1661890097.000000"
    },
    "last_read": "1661890181.670729",
    "subscribed": true,
    "reply_count": 2,
    "replies": [
      {
        "user": "U03P4005U76",
        "ts": "1661890161.227459"
      },
      {
        "user": "U03P4005U76",
        "ts": "1661890181.670729"
      }
    ],
    "latest_reply": "1661890181.670729",
    "team": "T03NM2X0JCR",
    "replace_original": false,
    "delete_original": false,
    "metadata": {
      "event_type": "",
      "event_payload": null
    },
    "blocks": [
      {
        "type": "rich_text",
        "block_id": "keHZu",
        "elements": [
          {
            "type": "rich_text_section",
            "elements": [
              {
                "type": "text",
                "text": "just a quick note on the lab: the last bonus is a bit stupid in my opinion... you don't have to bother about it too much, because Promise.all in this context doesn't quite work in the \"correct\" way. because it's not sequential at all."
              }
            ]
          }
        ]
      }
    ],
    "user_team": "T03NM2X0JCR",
    "source_team": "T03NM2X0JCR",
    "user_profile": {
      "avatar_hash": "19c4be189f84",
      "image_72": "https://avatars.slack-edge.com/2022-07-11/3783657200355_19c4be189f84d880b03e_72.jpg",
      "first_name": "Rico",
      "real_name": "Rico Trebeljahr",
      "display_name": "Rico Trebeljahr",
      "team": "T03NM2X0JCR",
      "name": "rico.trebeljahr",
      "is_restricted": false,
      "is_ultra_restricted": false
    },
    "reply_users_count": 1,
    "reply_users": [
      "U03P4005U76"
    ]
  },
  {
    "client_msg_id": "3a864255-7a67-4c0d-bae2-90e98e44258d",
    "type": "message",
    "user": "U03P4005U76",
    "text": "meaning that all you will do is to wait until all the steps are done, and then, update the display for everything at once.",
    "ts": "1661890161.227459",
    "thread_ts": "1661890083.559969",
    "parent_user_id": "U03P4005U76",
    "team": "T03NM2X0JCR",
    "replace_original": false,
    "delete_original": false,
    "metadata": {
      "event_type": "",
      "event_payload": null
    },
    "blocks": [
      {
        "type": "rich_text",
        "block_id": "BT9u",
        "elements": [
          {
            "type": "rich_text_section",
            "elements": [
              {
                "type": "text",
                "text": "meaning that all you will do is to wait until all the steps are done, and then, update the display for everything at once."
              }
            ]
          }
        ]
      }
    ],
    "user_team": "T03NM2X0JCR",
    "source_team": "T03NM2X0JCR",
    "user_profile": {
      "avatar_hash": "19c4be189f84",
      "image_72": "https://avatars.slack-edge.com/2022-07-11/3783657200355_19c4be189f84d880b03e_72.jpg",
      "first_name": "Rico",
      "real_name": "Rico Trebeljahr",
      "display_name": "Rico Trebeljahr",
      "team": "T03NM2X0JCR",
      "name": "rico.trebeljahr",
      "is_restricted": false,
      "is_ultra_restricted": false
    },
    "reply_users_count": 0,
    "reply_users": null
  },
  {
    "client_msg_id": "f38dd08e-3616-47a1-8526-e119692d97b4",
    "type": "message",
    "user": "U03P4005U76",
    "text": "unlike the other iterations, where it goes step by step.",
    "ts": "1661890181.670729",
    "thread_ts": "1661890083.559969",
    "parent_user_id": "U03P4005U76",
    "team": "T03NM2X0JCR",
    "replace_original": false,
    "delete_original": false,
    "metadata": {
      "event_type": "",
      "event_payload": null
    },
    "blocks": [
      {
        "type": "rich_text",
        "block_id": "wKfVq",
        "elements": [
          {
            "type": "rich_text_section",
            "elements": [
              {
                "type": "text",
                "text": "unlike the other iterations, where it goes step by step."
              }
            ]
          }
        ]
      }
    ],
    "user_team": "T03NM2X0JCR",
    "source_team": "T03NM2X0JCR",
    "user_profile": {
      "avatar_hash": "19c4be189f84",
      "image_72": "https://avatars.slack-edge.com/2022-07-11/3783657200355_19c4be189f84d880b03e_72.jpg",
      "first_name": "Rico",
      "real_name": "Rico Trebeljahr",
      "display_name": "Rico Trebeljahr",
      "team": "T03NM2X0JCR",
      "name": "rico.trebeljahr",
      "is_restricted": false,
      "is_ultra_restricted": false
    },
    "reply_users_count": 0,
    "reply_users": null
  }
]
