[
  {
    "client_msg_id": "3829109f-0078-4320-9511-9393167ed1df",
    "type": "message",
    "user": "U03NJ0V8G2W",
    "text": "I am gonna be late for class today :male_vampire:",
    "ts": "1669741317.842009",
    "thread_ts": "1669741317.842009",
    "last_read": "1669742572.680919",
    "subscribed": true,
    "reply_count": 2,
    "replies": [
      {
        "user": "U03P4005U76",
        "ts": "1669742559.213889"
      },
      {
        "user": "U03P4005U76",
        "ts": "1669742572.680919"
      }
    ],
    "latest_reply": "1669742572.680919",
    "team": "T03NM2X0JCR",
    "replace_original": false,
    "delete_original": false,
    "metadata": {
      "event_type": "",
      "event_payload": null
    },
    "blocks": [
      {
        "type": "rich_text",
        "block_id": "znfs5",
        "elements": [
          {
            "type": "rich_text_section",
            "elements": [
              {
                "type": "text",
                "text": "I am gonna be late for class today "
              },
              {
                "type": "emoji",
                "name": "male_vampire",
                "skin_tone": 0
              }
            ]
          }
        ]
      }
    ],
    "user_team": "T03NM2X0JCR",
    "source_team": "T03NM2X0JCR",
    "user_profile": {
      "avatar_hash": "193d3988ff32",
      "image_72": "https://avatars.slack-edge.com/2022-07-06/3760201470326_193d3988ff32e024463a_72.jpg",
      "first_name": "bernd",
      "real_name": "bernd havekost",
      "display_name": "bernd",
      "team": "T03NM2X0JCR",
      "name": "bernd",
      "is_restricted": false,
      "is_ultra_restricted": false
    },
    "reply_users_count": 1,
    "reply_users": [
      "U03P4005U76"
    ]
  },
  {
    "client_msg_id": "c692c3d7-28a9-43ea-92ac-edfbd8bfbad8",
    "type": "message",
    "user": "U03P4005U76",
    "text": "the vampire emoji :see_no_evil: :lel:",
    "ts": "1669742559.213889",
    "thread_ts": "1669741317.842009",
    "parent_user_id": "U03NJ0V8G2W",
    "team": "T03NM2X0JCR",
    "replace_original": false,
    "delete_original": false,
    "metadata": {
      "event_type": "",
      "event_payload": null
    },
    "blocks": [
      {
        "type": "rich_text",
        "block_id": "FHg5g",
        "elements": [
          {
            "type": "rich_text_section",
            "elements": [
              {
                "type": "text",
                "text": "the vampire emoji "
              },
              {
                "type": "emoji",
                "name": "see_no_evil",
                "skin_tone": 0
              },
              {
                "type": "text",
                "text": " "
              },
              {
                "type": "emoji",
                "name": "lel",
                "skin_tone": 0
              }
            ]
          }
        ]
      }
    ],
    "user_team": "T03NM2X0JCR",
    "source_team": "T03NM2X0JCR",
    "user_profile": {
      "avatar_hash": "19c4be189f84",
      "image_72": "https://avatars.slack-edge.com/2022-07-11/3783657200355_19c4be189f84d880b03e_72.jpg",
      "first_name": "Rico",
      "real_name": "Rico Trebeljahr",
      "display_name": "Rico Trebeljahr",
      "team": "T03NM2X0JCR",
      "name": "rico.trebeljahr",
      "is_restricted": false,
      "is_ultra_restricted": false
    },
    "reply_users_count": 0,
    "reply_users": null
  },
  {
    "client_msg_id": "6a50f3e6-28cb-4b2e-a285-8972331b15b3",
    "type": "message",
    "user": "U03P4005U76",
    "text": "no worries, it's only standup and project time anyways :slightly_smiling_face:",
    "ts": "1669742572.680919",
    "thread_ts": "1669741317.842009",
    "parent_user_id": "U03NJ0V8G2W",
    "team": "T03NM2X0JCR",
    "replace_original": false,
    "delete_original": false,
    "metadata": {
      "event_type": "",
      "event_payload": null
    },
    "blocks": [
      {
        "type": "rich_text",
        "block_id": "86rA",
        "elements": [
          {
            "type": "rich_text_section",
            "elements": [
              {
                "type": "text",
                "text": "no worries, it's only standup and project time anyways "
              },
              {
                "type": "emoji",
                "name": "slightly_smiling_face",
                "skin_tone": 0
              }
            ]
          }
        ]
      }
    ],
    "user_team": "T03NM2X0JCR",
    "source_team": "T03NM2X0JCR",
    "user_profile": {
      "avatar_hash": "19c4be189f84",
      "image_72": "https://avatars.slack-edge.com/2022-07-11/3783657200355_19c4be189f84d880b03e_72.jpg",
      "first_name": "Rico",
      "real_name": "Rico Trebeljahr",
      "display_name": "Rico Trebeljahr",
      "team": "T03NM2X0JCR",
      "name": "rico.trebeljahr",
      "is_restricted": false,
      "is_ultra_restricted": false
    },
    "reply_users_count": 0,
    "reply_users": null
  },
  {
    "client_msg_id": "0e9f25e5-dbb4-4d76-8e05-711661afcb46",
    "type": "message",
    "user": "U03NBCRJ99U",
    "text": "Hi! no goodbye today?",
    "ts": "1669752065.016029",
    "team": "T03NM2X0JCR",
    "replace_original": false,
    "delete_original": false,
    "metadata": {
      "event_type": "",
      "event_payload": null
    },
    "blocks": [
      {
        "type": "rich_text",
        "block_id": "hS1RT",
        "elements": [
          {
            "type": "rich_text_section",
            "elements": [
              {
                "type": "text",
                "text": "Hi! no goodbye today?"
              }
            ]
          }
        ]
      }
    ],
    "user_team": "T03NM2X0JCR",
    "source_team": "T03NM2X0JCR",
    "user_profile": {
      "avatar_hash": "g573a376398a",
      "image_72": "https://secure.gravatar.com/avatar/573a376398a82acb061e12fb20ba25f7.jpg?s=72\u0026d=https%3A%2F%2Fa.slack-edge.com%2Fdf10d%2Fimg%2Favatars%2Fava_0010-72.png",
      "first_name": "Antonio",
      "real_name": "Antonio Vara Piquer",
      "display_name": "",
      "team": "T03NM2X0JCR",
      "name": "ghezath",
      "is_restricted": false,
      "is_ultra_restricted": false
    },
    "reply_users_count": 0,
    "reply_users": null
  },
  {
    "client_msg_id": "f8953d66-b2f2-4fc0-be8e-4c6903f959c5",
    "type": "message",
    "user": "U03NBCRJ99U",
    "text": "30 min more",
    "ts": "1669752078.512849",
    "team": "T03NM2X0JCR",
    "replace_original": false,
    "delete_original": false,
    "metadata": {
      "event_type": "",
      "event_payload": null
    },
    "blocks": [
      {
        "type": "rich_text",
        "block_id": "1UoM6",
        "elements": [
          {
            "type": "rich_text_section",
            "elements": [
              {
                "type": "text",
                "text": "30 min more"
              }
            ]
          }
        ]
      }
    ],
    "user_team": "T03NM2X0JCR",
    "source_team": "T03NM2X0JCR",
    "user_profile": {
      "avatar_hash": "g573a376398a",
      "image_72": "https://secure.gravatar.com/avatar/573a376398a82acb061e12fb20ba25f7.jpg?s=72\u0026d=https%3A%2F%2Fa.slack-edge.com%2Fdf10d%2Fimg%2Favatars%2Fava_0010-72.png",
      "first_name": "Antonio",
      "real_name": "Antonio Vara Piquer",
      "display_name": "",
      "team": "T03NM2X0JCR",
      "name": "ghezath",
      "is_restricted": false,
      "is_ultra_restricted": false
    },
    "reply_users_count": 0,
    "reply_users": null
  },
  {
    "client_msg_id": "157fce5e-66ff-4877-b7bd-426c08d5c891",
    "type": "message",
    "user": "U03P4005U76",
    "text": "wait isn't it 21:01 right now?",
    "ts": "1669752081.009979",
    "team": "T03NM2X0JCR",
    "replace_original": false,
    "delete_original": false,
    "metadata": {
      "event_type": "",
      "event_payload": null
    },
    "blocks": [
      {
        "type": "rich_text",
        "block_id": "iqe=",
        "elements": [
          {
            "type": "rich_text_section",
            "elements": [
              {
                "type": "text",
                "text": "wait isn't it 21:01 right now?"
              }
            ]
          }
        ]
      }
    ],
    "user_team": "T03NM2X0JCR",
    "source_team": "T03NM2X0JCR",
    "user_profile": {
      "avatar_hash": "19c4be189f84",
      "image_72": "https://avatars.slack-edge.com/2022-07-11/3783657200355_19c4be189f84d880b03e_72.jpg",
      "first_name": "Rico",
      "real_name": "Rico Trebeljahr",
      "display_name": "Rico Trebeljahr",
      "team": "T03NM2X0JCR",
      "name": "rico.trebeljahr",
      "is_restricted": false,
      "is_ultra_restricted": false
    },
    "reply_users_count": 0,
    "reply_users": null
  },
  {
    "client_msg_id": "80a25421-0270-43e6-ac28-98e9bf5cb031",
    "type": "message",
    "user": "U03NBCRJ99U",
    "text": "sorry",
    "ts": "1669752081.225309",
    "team": "T03NM2X0JCR",
    "replace_original": false,
    "delete_original": false,
    "metadata": {
      "event_type": "",
      "event_payload": null
    },
    "blocks": [
      {
        "type": "rich_text",
        "block_id": "/AHt",
        "elements": [
          {
            "type": "rich_text_section",
            "elements": [
              {
                "type": "text",
                "text": "sorry"
              }
            ]
          }
        ]
      }
    ],
    "user_team": "T03NM2X0JCR",
    "source_team": "T03NM2X0JCR",
    "user_profile": {
      "avatar_hash": "g573a376398a",
      "image_72": "https://secure.gravatar.com/avatar/573a376398a82acb061e12fb20ba25f7.jpg?s=72\u0026d=https%3A%2F%2Fa.slack-edge.com%2Fdf10d%2Fimg%2Favatars%2Fava_0010-72.png",
      "first_name": "Antonio",
      "real_name": "Antonio Vara Piquer",
      "display_name": "",
      "team": "T03NM2X0JCR",
      "name": "ghezath",
      "is_restricted": false,
      "is_ultra_restricted": false
    },
    "reply_users_count": 0,
    "reply_users": null
  },
  {
    "client_msg_id": "dc9f42ac-11f4-4964-829e-d714f250aa22",
    "type": "message",
    "user": "U03P4005U76",
    "text": "haha I am confused now.",
    "ts": "1669752088.809409",
    "team": "T03NM2X0JCR",
    "replace_original": false,
    "delete_original": false,
    "metadata": {
      "event_type": "",
      "event_payload": null
    },
    "blocks": [
      {
        "type": "rich_text",
        "block_id": "OozV",
        "elements": [
          {
            "type": "rich_text_section",
            "elements": [
              {
                "type": "text",
                "text": "haha I am confused now."
              }
            ]
          }
        ]
      }
    ],
    "user_team": "T03NM2X0JCR",
    "source_team": "T03NM2X0JCR",
    "user_profile": {
      "avatar_hash": "19c4be189f84",
      "image_72": "https://avatars.slack-edge.com/2022-07-11/3783657200355_19c4be189f84d880b03e_72.jpg",
      "first_name": "Rico",
      "real_name": "Rico Trebeljahr",
      "display_name": "Rico Trebeljahr",
      "team": "T03NM2X0JCR",
      "name": "rico.trebeljahr",
      "is_restricted": false,
      "is_ultra_restricted": false
    },
    "reply_users_count": 0,
    "reply_users": null
  },
  {
    "client_msg_id": "89fad12c-8b90-4858-9235-1dd7bf94eb99",
    "type": "message",
    "user": "U03P4005U76",
    "text": "I have my laptop intentionally set to the \"wrong\" time for Tenerife, which is the German time which is the time of the bootcamp and it says 21:02 so see you in 23 mins I guess?",
    "ts": "1669752130.950239",
    "team": "T03NM2X0JCR",
    "replace_original": false,
    "delete_original": false,
    "metadata": {
      "event_type": "",
      "event_payload": null
    },
    "blocks": [
      {
        "type": "rich_text",
        "block_id": "z4PK",
        "elements": [
          {
            "type": "rich_text_section",
            "elements": [
              {
                "type": "text",
                "text": "I have my laptop intentionally set to the \"wrong\" time for Tenerife, which is the German time which is the time of the bootcamp and it says 21:02 so see you in 23 mins I guess?"
              }
            ]
          }
        ]
      }
    ],
    "user_team": "T03NM2X0JCR",
    "source_team": "T03NM2X0JCR",
    "user_profile": {
      "avatar_hash": "19c4be189f84",
      "image_72": "https://avatars.slack-edge.com/2022-07-11/3783657200355_19c4be189f84d880b03e_72.jpg",
      "first_name": "Rico",
      "real_name": "Rico Trebeljahr",
      "display_name": "Rico Trebeljahr",
      "team": "T03NM2X0JCR",
      "name": "rico.trebeljahr",
      "is_restricted": false,
      "is_ultra_restricted": false
    },
    "reply_users_count": 0,
    "reply_users": null
  },
  {
    "client_msg_id": "7eb5696d-eeea-44e6-9867-18f48c9930ef",
    "type": "message",
    "user": "U03P4005U76",
    "text": "but for a second you had me really worried that it switched time to something wrong haha :man-shrugging:",
    "ts": "1669752150.153339",
    "team": "T03NM2X0JCR",
    "replace_original": false,
    "delete_original": false,
    "metadata": {
      "event_type": "",
      "event_payload": null
    },
    "blocks": [
      {
        "type": "rich_text",
        "block_id": "Lpa3j",
        "elements": [
          {
            "type": "rich_text_section",
            "elements": [
              {
                "type": "text",
                "text": "but for a second you had me really worried that it switched time to something wrong haha "
              },
              {
                "type": "emoji",
                "name": "man-shrugging",
                "skin_tone": 0
              }
            ]
          }
        ]
      }
    ],
    "user_team": "T03NM2X0JCR",
    "source_team": "T03NM2X0JCR",
    "user_profile": {
      "avatar_hash": "19c4be189f84",
      "image_72": "https://avatars.slack-edge.com/2022-07-11/3783657200355_19c4be189f84d880b03e_72.jpg",
      "first_name": "Rico",
      "real_name": "Rico Trebeljahr",
      "display_name": "Rico Trebeljahr",
      "team": "T03NM2X0JCR",
      "name": "rico.trebeljahr",
      "is_restricted": false,
      "is_ultra_restricted": false
    },
    "reply_users_count": 0,
    "reply_users": null
  },
  {
    "client_msg_id": "96b2cc92-3d94-44f8-bd10-b252dacbdfd7",
    "type": "message",
    "user": "U03NBCRJ99U",
    "text": ":rolling_on_the_floor_laughing:",
    "ts": "1669752155.232339",
    "team": "T03NM2X0JCR",
    "replace_original": false,
    "delete_original": false,
    "metadata": {
      "event_type": "",
      "event_payload": null
    },
    "blocks": [
      {
        "type": "rich_text",
        "block_id": "n7=mP",
        "elements": [
          {
            "type": "rich_text_section",
            "elements": [
              {
                "type": "emoji",
                "name": "rolling_on_the_floor_laughing",
                "skin_tone": 0
              }
            ]
          }
        ]
      }
    ],
    "user_team": "T03NM2X0JCR",
    "source_team": "T03NM2X0JCR",
    "user_profile": {
      "avatar_hash": "g573a376398a",
      "image_72": "https://secure.gravatar.com/avatar/573a376398a82acb061e12fb20ba25f7.jpg?s=72\u0026d=https%3A%2F%2Fa.slack-edge.com%2Fdf10d%2Fimg%2Favatars%2Fava_0010-72.png",
      "first_name": "Antonio",
      "real_name": "Antonio Vara Piquer",
      "display_name": "",
      "team": "T03NM2X0JCR",
      "name": "ghezath",
      "is_restricted": false,
      "is_ultra_restricted": false
    },
    "reply_users_count": 0,
    "reply_users": null
  },
  {
    "client_msg_id": "caf3e4cb-9aa6-4300-b4cf-5b82ef75d01a",
    "type": "message",
    "user": "U03NJ0VSF8A",
    "text": "Antonio is ready to GO! :slightly_smiling_face:",
    "ts": "1669752718.742589",
    "team": "T03NM2X0JCR",
    "reactions": [
      {
        "name": "fire",
        "count": 1,
        "users": [
          "U03NF3FU4CD"
        ]
      }
    ],
    "replace_original": false,
    "delete_original": false,
    "metadata": {
      "event_type": "",
      "event_payload": null
    },
    "blocks": [
      {
        "type": "rich_text",
        "block_id": "qY3z",
        "elements": [
          {
            "type": "rich_text_section",
            "elements": [
              {
                "type": "text",
                "text": "Antonio is ready to GO! "
              },
              {
                "type": "emoji",
                "name": "slightly_smiling_face",
                "skin_tone": 0
              }
            ]
          }
        ]
      }
    ],
    "user_team": "T03NM2X0JCR",
    "source_team": "T03NM2X0JCR",
    "user_profile": {
      "avatar_hash": "04411a049b06",
      "image_72": "https://avatars.slack-edge.com/2022-07-14/3795254892613_04411a049b06f552bb4d_72.jpg",
      "first_name": "Joshua",
      "real_name": "Joshua LaMorey-Salzmann",
      "display_name": "Joshua",
      "team": "T03NM2X0JCR",
      "name": "lamorey.joshua",
      "is_restricted": false,
      "is_ultra_restricted": false
    },
    "reply_users_count": 0,
    "reply_users": null
  },
  {
    "client_msg_id": "7d070823-a33e-4cb7-8fc7-20bafcd0b2b9",
    "type": "message",
    "user": "U03NF3FU4CD",
    "text": "\u003chttps://tenor.com/becCk.gif\u003e",
    "ts": "1669752861.517569",
    "attachments": [
      {
        "fallback": "303x498px image",
        "id": 1,
        "image_url": "https://tenor.com/becCk.gif",
        "from_url": "https://tenor.com/becCk.gif",
        "original_url": "https://tenor.com/becCk.gif",
        "blocks": null
      }
    ],
    "team": "T03NM2X0JCR",
    "replace_original": false,
    "delete_original": false,
    "metadata": {
      "event_type": "",
      "event_payload": null
    },
    "blocks": [
      {
        "type": "rich_text",
        "block_id": "pJY",
        "elements": [
          {
            "type": "rich_text_section",
            "elements": [
              {
                "type": "link",
                "url": "https://tenor.com/becCk.gif",
                "text": ""
              }
            ]
          }
        ]
      }
    ],
    "user_team": "T03NM2X0JCR",
    "source_team": "T03NM2X0JCR",
    "user_profile": {
      "avatar_hash": "gffbd1f8138d",
      "image_72": "https://secure.gravatar.com/avatar/ffbd1f8138d8ce7282914f927aa4c382.jpg?s=72\u0026d=https%3A%2F%2Fa.slack-edge.com%2Fdf10d%2Fimg%2Favatars%2Fava_0000-72.png",
      "first_name": "Hector",
      "real_name": "Hector Fernandez",
      "display_name": "",
      "team": "T03NM2X0JCR",
      "name": "hfernandez04",
      "is_restricted": false,
      "is_ultra_restricted": false
    },
    "reply_users_count": 0,
    "reply_users": null
  },
  {
    "client_msg_id": "fd5e36a2-c305-4d8a-82e2-a94a59b01ce7",
    "type": "message",
    "user": "U03P4005U76",
    "text": "this channel turned into random really quickly haha",
    "ts": "1669752883.372209",
    "team": "T03NM2X0JCR",
    "reactions": [
      {
        "name": "rolling_on_the_floor_laughing",
        "count": 1,
        "users": [
          "U03NF3FU4CD"
        ]
      }
    ],
    "replace_original": false,
    "delete_original": false,
    "metadata": {
      "event_type": "",
      "event_payload": null
    },
    "blocks": [
      {
        "type": "rich_text",
        "block_id": "luH",
        "elements": [
          {
            "type": "rich_text_section",
            "elements": [
              {
                "type": "text",
                "text": "this channel turned into random really quickly haha"
              }
            ]
          }
        ]
      }
    ],
    "user_team": "T03NM2X0JCR",
    "source_team": "T03NM2X0JCR",
    "user_profile": {
      "avatar_hash": "19c4be189f84",
      "image_72": "https://avatars.slack-edge.com/2022-07-11/3783657200355_19c4be189f84d880b03e_72.jpg",
      "first_name": "Rico",
      "real_name": "Rico Trebeljahr",
      "display_name": "Rico Trebeljahr",
      "team": "T03NM2X0JCR",
      "name": "rico.trebeljahr",
      "is_restricted": false,
      "is_ultra_restricted": false
    },
    "reply_users_count": 0,
    "reply_users": null
  },
  {
    "client_msg_id": "3c04a5a4-29c9-445d-a6c2-2b54fa962140",
    "type": "message",
    "user": "U03NBCRJ99U",
    "text": "not the only one tired :roll-safe:",
    "ts": "1669752949.420169",
    "team": "T03NM2X0JCR",
    "reactions": [
      {
        "name": "hand",
        "count": 1,
        "users": [
          "U03NF3FU4CD"
        ]
      },
      {
        "name": "hand::skin-tone-3",
        "count": 1,
        "users": [
          "U03NJ0VSF8A"
        ]
      }
    ],
    "replace_original": false,
    "delete_original": false,
    "metadata": {
      "event_type": "",
      "event_payload": null
    },
    "blocks": [
      {
        "type": "rich_text",
        "block_id": "d5Gai",
        "elements": [
          {
            "type": "rich_text_section",
            "elements": [
              {
                "type": "text",
                "text": "not the only one tired "
              },
              {
                "type": "emoji",
                "name": "roll-safe",
                "skin_tone": 0
              }
            ]
          }
        ]
      }
    ],
    "user_team": "T03NM2X0JCR",
    "source_team": "T03NM2X0JCR",
    "user_profile": {
      "avatar_hash": "g573a376398a",
      "image_72": "https://secure.gravatar.com/avatar/573a376398a82acb061e12fb20ba25f7.jpg?s=72\u0026d=https%3A%2F%2Fa.slack-edge.com%2Fdf10d%2Fimg%2Favatars%2Fava_0010-72.png",
      "first_name": "Antonio",
      "real_name": "Antonio Vara Piquer",
      "display_name": "",
      "team": "T03NM2X0JCR",
      "name": "ghezath",
      "is_restricted": false,
      "is_ultra_restricted": false
    },
    "reply_users_count": 0,
    "reply_users": null
  },
  {
    "client_msg_id": "7ff342dc-de8b-43e2-ba21-fd57f451660c",
    "type": "message",
    "user": "U03NJ0V8G2W",
    "text": "Sorry, my daughter woke up... See you Thursday!",
    "ts": "1669753622.804909",
    "thread_ts": "1669753622.804909",
    "reply_count": 1,
    "replies": [
      {
        "user": "U03NF3FU4CD",
        "ts": "1669753838.831349"
      }
    ],
    "latest_reply": "1669753838.831349",
    "team": "T03NM2X0JCR",
    "replace_original": false,
    "delete_original": false,
    "metadata": {
      "event_type": "",
      "event_payload": null
    },
    "blocks": [
      {
        "type": "rich_text",
        "block_id": "Hr1M+",
        "elements": [
          {
            "type": "rich_text_section",
            "elements": [
              {
                "type": "text",
                "text": "Sorry, my daughter woke up... See you Thursday!"
              }
            ]
          }
        ]
      }
    ],
    "user_team": "T03NM2X0JCR",
    "source_team": "T03NM2X0JCR",
    "user_profile": {
      "avatar_hash": "193d3988ff32",
      "image_72": "https://avatars.slack-edge.com/2022-07-06/3760201470326_193d3988ff32e024463a_72.jpg",
      "first_name": "bernd",
      "real_name": "bernd havekost",
      "display_name": "bernd",
      "team": "T03NM2X0JCR",
      "name": "bernd",
      "is_restricted": false,
      "is_ultra_restricted": false
    },
    "reply_users_count": 1,
    "reply_users": [
      "U03NF3FU4CD"
    ]
  },
  {
    "client_msg_id": "bfd14559-3308-4b9d-8709-6a99693d96f5",
    "type": "message",
    "user": "U03NF3FU4CD",
    "text": "Have  a nice evening! :slightly_smiling_face:",
    "ts": "1669753838.831349",
    "thread_ts": "1669753622.804909",
    "parent_user_id": "U03NJ0V8G2W",
    "team": "T03NM2X0JCR",
    "replace_original": false,
    "delete_original": false,
    "metadata": {
      "event_type": "",
      "event_payload": null
    },
    "blocks": [
      {
        "type": "rich_text",
        "block_id": "oBFqX",
        "elements": [
          {
            "type": "rich_text_section",
            "elements": [
              {
                "type": "text",
                "text": "Have  a nice evening! "
              },
              {
                "type": "emoji",
                "name": "slightly_smiling_face",
                "skin_tone": 0
              }
            ]
          }
        ]
      }
    ],
    "user_team": "T03NM2X0JCR",
    "source_team": "T03NM2X0JCR",
    "user_profile": {
      "avatar_hash": "gffbd1f8138d",
      "image_72": "https://secure.gravatar.com/avatar/ffbd1f8138d8ce7282914f927aa4c382.jpg?s=72\u0026d=https%3A%2F%2Fa.slack-edge.com%2Fdf10d%2Fimg%2Favatars%2Fava_0000-72.png",
      "first_name": "Hector",
      "real_name": "Hector Fernandez",
      "display_name": "",
      "team": "T03NM2X0JCR",
      "name": "hfernandez04",
      "is_restricted": false,
      "is_ultra_restricted": false
    },
    "reply_users_count": 0,
    "reply_users": null
  }
]
