[
  {
    "client_msg_id": "b6b0638d-cfdf-414d-9598-e9a08a20f0f8",
    "type": "message",
    "user": "U03NKPQSAA0",
    "text": "Hello \u003c!channel\u003e,\nI hope you are all doing well :blush: It was a pleasure talking a bit with you during the 1on1s week!\n\nFor the berliners, next Wednesday (2nd of November) we will organise an Ironbeers event :beers:\nIt will be a special Halloween theme, so come with your costumes :jack_o_lantern:\nFrom 6 to 8pm on the 5th floor. See you there hopefully!!!",
    "ts": "1666951590.988659",
    "team": "T03NM2X0JCR",
    "replace_original": false,
    "delete_original": false,
    "metadata": {
      "event_type": "",
      "event_payload": null
    },
    "blocks": [
      {
        "type": "rich_text",
        "block_id": "r=2",
        "elements": [
          {
            "type": "rich_text_section",
            "elements": [
              {
                "type": "text",
                "text": "Hello "
              },
              {
                "type": "broadcast",
                "range": "channel"
              },
              {
                "type": "text",
                "text": ",\nI hope you are all doing well "
              },
              {
                "type": "emoji",
                "name": "blush",
                "skin_tone": 0
              },
              {
                "type": "text",
                "text": " It was a pleasure talking a bit with you during the 1on1s week!\n\nFor the berliners, next Wednesday (2nd of November) we will organise an Ironbeers event "
              },
              {
                "type": "emoji",
                "name": "beers",
                "skin_tone": 0
              },
              {
                "type": "text",
                "text": "\nIt will be a special Halloween theme, so come with your costumes "
              },
              {
                "type": "emoji",
                "name": "jack_o_lantern",
                "skin_tone": 0
              },
              {
                "type": "text",
                "text": "\nFrom 6 to 8pm on the 5th floor. See you there hopefully!!!"
              }
            ]
          }
        ]
      }
    ],
    "user_team": "T03NM2X0JCR",
    "source_team": "T03NM2X0JCR",
    "user_profile": {
      "avatar_hash": "161b83e3a9a4",
      "image_72": "https://avatars.slack-edge.com/2022-10-18/4224394580103_161b83e3a9a4989c5f84_72.png",
      "first_name": "Joyce",
      "real_name": "Joyce Bride - Program",
      "display_name": "Joyce Bride",
      "team": "T03NM2X0JCR",
      "name": "joyce.bride",
      "is_restricted": false,
      "is_ultra_restricted": false
    },
    "reply_users_count": 0,
    "reply_users": null
  }
]
